{
    "name": "我的心太乱",
    "id": 156404,
    "artist": "周传雄",
    "artistid": 2,
    "pic": "https://img4.kuwo.cn/star/albumcover/120/s4s78/87/4040351063.jpg",
    "releasedate": "1997-10-30",
    "duration": 293,
    "album": "我的心太乱",
    "original_url": "https://www.kuwo.cn/play_detail/156404",
    "lyrics": "我的心太乱 - 周传雄\n词：丁晓雯\n曲：小刚\n编曲：鲍比达\n夜里难以入睡\n用什么可以麻醉\n情绪太多 怎堪面对\n不是不要你陪\n有些事你无法体会\n卸下了防备 孤独跟随\n我想要一个 自己的空间\n能够好好想想我们之间的明天\n如果爱情不如我们想象的甜美\n那么所有的罪让我来背\n我的心太乱 要一些空白\n你若是明白 让我暂时的离开\n我的心太乱 不敢再贪更多爱\n想哭的我 却怎么哭也哭不出来\n我的心太乱 要一些空白\n老天在不在 忘了为我来安排\n我的心太乱 害怕爱情的背叛\n想哭的我 像是一个迷路小孩\n迷路的小孩\n夜里难以入睡\n用什么可以麻醉\n情绪太多 怎堪面对\n不是不要你陪\n有些事你无法体会\n卸下了防备 孤独跟随\n我想要一个 自己的空间\n能够好好想想我们之间的明天\n如果爱情不如我们想象的甜美\n那么所有的罪让我来背\n我的心太乱 要一些空白\n你若是明白 让我暂时的离开\n我的心太乱 不敢再贪更多爱\n想哭的我 却怎么哭也哭不出来\n我的心太乱 要一些空白\n老天在不在 忘了为我来安排\n我的心太乱 害怕爱情的背叛\n想哭的我 像是一个迷路小孩\n迷路的小孩\n我的心太乱 要一些空白\n你若是明白 让我暂时的离开\n我的心太乱 不敢再贪更多爱\n想哭的我 却怎么哭也哭不出来\n我的心太乱 要一些空白\n老天在不在 忘了为我来安排\n我的心太乱 害怕爱情的背叛\n想哭的我 像是一个迷路小孩\n迷路的小孩\n",
    "comments": [
        {
            "content": "可以帮我顶一下吗，我很想找到10多年没联系的好朋友了。",
            "username": "飞",
            "time": "2016-08-24 16:35:51"
        },
        {
            "content": "有时候，喜欢一首歌不是因为歌唱的有多好听，而是因为歌词写的像自己，音乐这东西，开心时入耳，伤心时入心。快乐的时候你听的是音乐，难过的时候你懂得了歌词！爱一首歌…，常常是因为某句歌词。但真正动人的不是某句歌词，而是在你生命中那些关于歌词的故事……………😊",
            "username": "相濡",
            "time": "2016-10-18 08:50:45"
        },
        {
            "content": "小辣椒，还记得吗？这是我们最喜欢的一首歌。",
            "username": "飞",
            "time": "2016-08-24 16:34:43"
        },
        {
            "content": "你在《黄昏》时分，打开《记事本》，在《关不上的窗》 前嘘叹《寂寞沙洲冷》。你祈祷在《蓝色土耳其》能有一片属于你的《男人海洋》。你说《弱水三千》你只取一瓢饮，《时不知归》，归不知时，这不是《爱的告别式》。我们曾经都是《追赶时间的少年》，都拥有《空心》的感受。最后，你要《再出发》，抛开曾经的《坏感觉》。我说《我也许是个笑话》改变不了你《孤单的习惯》。《有没有一首歌会让你想起我》，如阵阵《暖风》，如散漫《花香》，如《满院落叶》。我送你搭乘《末班车》，在窗外看着你，你的眼神《出卖》了你的感情。杨柳岸，晓风残月，《今宵酒醒何处》。从此身边没有了你，回忆曾经，在《星空下》，想起了我们默守的《冬天的秘密》。",
            "username": "翻了身的咸鱼～！",
            "time": "2019-04-10 21:37:21"
        },
        {
            "content": "我的心太乱，有一点空白，就像关不上的窗，谁能填补他的无奈",
            "username": "果坚",
            "time": "2017-01-07 00:22:51"
        }
    ]
}