{
    "name": "月亮惹的祸",
    "id": 158361,
    "artist": "张宇",
    "artistid": 1209,
    "pic": "https://img4.kuwo.cn/star/albumcover/120/s4s16/76/1918953682.jpg",
    "releasedate": "1998-12-08",
    "duration": 262,
    "album": "月亮 太阳",
    "original_url": "https://www.kuwo.cn/play_detail/158361",
    "lyrics": "月亮惹的祸 - 张宇 (Phil Chang)\n词：十一郎\n曲：张宇\n都是你的错轻易爱上我\n让我不知不觉满足被爱的虚荣\n都是你的错你对人的宠\n是一种诱惑\n都是你的错在你的眼中\n总是藏着让人又爱又怜的朦胧\n都是你的错你的痴情梦\n像一个魔咒\n被你爱过还能为谁蠢动\n我承认都是月亮惹的祸\n那样的夜色太美你太温柔\n才会在刹那之间\n只想和你一起到白头\n我承认都是誓言惹的祸\n偏偏似糖如蜜说来最动人\n再怎么心如钢铁也成绕指柔\n都是你的错轻易爱上我\n让我不知不觉满足被爱的虚荣\n都是你的错你对人的宠\n是一种诱惑\n都是你的错在你的眼中\n总是藏着让人又爱又怜的朦胧\n都是你的错你的痴情梦\n像一个魔咒\n被你爱过还能为谁蠢动\n我承认都是月亮惹的祸\n那样的夜色太美你太温柔\n才会在刹那之间\n只想和你一起到白头\n我承认都是誓言惹的祸\n偏偏似糖如蜜说来最动人\n再怎么心如钢铁也成绕指柔\n怎样的情生意动\n会让两个人拿一生当承诺\n我承认都是誓言惹的祸\n偏偏似糖如蜜说来最动人\n再怎么心如钢铁也成绕指柔\n我承认都是月亮惹的祸\n那样的夜色太美你太温柔\n才会在刹那之间\n只想和你一起到白头\n我承认都是誓言惹的祸\n偏偏似糖如蜜说来最动人\n再怎么心如钢铁也成绕指柔\n",
    "comments": [
        {
            "content": "看来不服老不行了。只有老歌才符合我的胃口了。。。。。。。",
            "username": "晒得黑",
            "time": "2017-01-18 14:09:37"
        },
        {
            "content": "喜欢这种悲伤的情歌，不是假的，只要经历过你就会发现，那些歌词里写得都是真的",
            "username": "ford",
            "time": "2017-03-01 06:20:07"
        },
        {
            "content": "八零后们，请点我。我们老了么",
            "username": "2452477866",
            "time": "2017-04-23 22:35:28"
        },
        {
            "content": "月光照到我房间，让我忧郁起来，为什么会突然想起你，一个伤我那么深的人，都是月亮惹的祸。",
            "username": "LeeKamPi",
            "time": "2017-04-06 08:10:12"
        },
        {
            "content": "每次听到这首歌就能想到你，那时候你用电播送给我的……山东济宁刘峰",
            "username": "Mary",
            "time": "2016-11-10 19:28:46"
        }
    ]
}