{
    "name": "故乡 (Live于2013.08.10哈尔滨站)",
    "id": 41434011,
    "artist": "许巍",
    "artistid": 1158,
    "pic": "https://img4.kuwo.cn/star/albumcover/120/21/92/2787883653.jpg",
    "releasedate": "2014-09-15",
    "duration": 366,
    "album": "此时此刻 演唱会 LIVE记录辑",
    "original_url": "https://www.kuwo.cn/play_detail/41434011",
    "lyrics": "故乡 (Live于2013.08.10哈尔滨站) - 许巍\n词：许巍\n曲：许巍\n天边夕阳再次映上我的脸庞\n再次映着我那不安的心\n这是什么地方依然是如此的荒凉\n那无尽的旅程如此漫长\n我是永远向着远方独行的浪子\n你是茫茫人海之中我的女人\n在异乡的路上每一个寒冷的夜晚\n这思念它如刀让我伤痛\n总是在梦里我看到你无助的双眼\n我的心又一次被唤醒\n我站在这里想起和你曾经离别情景\n你站在人群中间那么孤单\n那是你破碎的心\n我的心却那么狂野\n你在我的心里永远是故乡\n你总为我独自守候沉默等待\n在异乡的路上每一个寒冷的夜晚\n这思念它如刀让我伤痛\n总是在梦里我看到你无助的双眼\n我的心又一次被唤醒\n我站在这里想起和你曾经离别情景\n你站在人群中间那么孤单\n那是你破碎的心\n我的心却那么狂野\n总是在梦里我看到你无助的双眼\n我的心又一次被唤醒\n总是在梦里看到自己走在归乡路上\n你站在夕阳下面容颜娇艳\n那是你衣裙漫飞\n那是你温柔如水\n",
    "comments": [
        {
            "content": "专升本没考取，为了娶自己心爱的新疆女孩大专毕业证没拿就跑到广西打工。一路漂泊到昆明，丽江，贵州，大理，重庆，郑州，西安，保山，腾冲，拉萨。人已为他人妻，30而立依旧无法释怀。青春属于乌鲁木齐女孩和许巍。居无定所，浪荡漂泊，怀着那颗依旧没有改变浪迹天涯的心。",
            "username": "孤单",
            "time": "2018-06-23 14:46:15"
        },
        {
            "content": "我喜欢这个版本，前奏编曲风格很棒！",
            "username": "魔羯座",
            "time": "2018-08-29 11:52:08"
        },
        {
            "content": "融不进的他乡，回不去的故乡",
            "username": "ME",
            "time": "2018-06-23 14:47:35"
        },
        {
            "content": "说实话我觉得这是比录音棚版本更好听的版本",
            "username": "方方",
            "time": "2018-10-30 16:04:22"
        },
        {
            "content": "有多少被人刺到痛处的，让我看到你们老铁",
            "username": "一条大河",
            "time": "2018-07-03 21:17:29"
        }
    ]
}