{
    "name": "嘿，那个你",
    "id": 301152637,
    "artist": "房东的猫",
    "artistid": 251015,
    "pic": "https://img4.kuwo.cn/star/albumcover/120/s3s55/64/3431177019.png",
    "releasedate": "2023-09-13",
    "duration": 220,
    "album": "骄阳伴我 电视剧影视原声大碟",
    "original_url": "https://www.kuwo.cn/play_detail/301152637",
    "lyrics": "嘿，那个你 (《骄阳伴我》电视剧插曲) - 房东的猫\n词：纹东虎\n曲：蒋希伟\n编曲：蒋希伟\n主唱：王心怡@房东的猫\n和声：吴佩岭@房东的猫\n吉他：赵华玉\n钢琴：蒋希伟\n大提琴：张平\n弦乐编写：蒋希伟\n弦乐演奏：国际首席爱乐乐团\n乐团艺术总监：李朋\n录音棚：金田录音棚/尚摩悦声录音棚/毡房 (khos wy) 音乐工作室\n音频编辑：王宇鹏\n录音师：王小四/林杰\n配唱制作人：王冠博@尚摩悦声\n混音母带工程师：王磊@Allanwang Studio\n制作人：蒋希伟@观乐音乐工作室\n监制：金山/田甜/李纤橙\n发行：听见时代\n特别鸣谢：青柴文化\n驶向明天的电车\n有位特别的乘客\n她路过四季景色\n把春天给了我\n我留着每瓣花朵\n守着思念的河\n期盼了这一次相遇\n依然微笑着\n嘿 那个你啊\n下一站 我在这\n不灭的街灯\n从未散去温热\n哦 这个你啊\n别再远去了\n你的名字我依然还记得\n没有终点的电车\n左边留着的空座\n也许祝福太多了\n显得我更沉默\n我看到街边角落\n听到许多欢乐\n如果那相遇是偶然\n相知多难得\n嘿 那个你啊\n下一站 我在这\n不灭的街灯\n从未散去温热\n哦 这个你啊\n别再远去了\n牵挂你的心永远跳动着\n",
    "comments": [
        {
            "content": "嘿，那个你出电视剧歌了都，我还在云烟成雨徘徊呢！😂",
            "username": "叮当不叮当",
            "time": "2023-09-24 11:40:24"
        }
    ]
}