{
    "name": "我不愿 让你一个人",
    "id": 56062728,
    "artist": "五月天",
    "artistid": 354,
    "pic": "https://img4.kuwo.cn/star/albumcover/120/s4s99/41/3266298012.png",
    "releasedate": "2011-12-16",
    "duration": 265,
    "album": "第二人生（明日版）",
    "original_url": "https://www.kuwo.cn/play_detail/56062728",
    "lyrics": "我不愿 让你一个人 - 五月天 (Mayday)\n词：阿信\n曲：冠佑/阿信\n你说呢 明知你不在还是会问\n空气却不能代替你出声\n习惯像永不愈合的固执伤痕\n一思念就撕裂灵魂\n把相片让你能保存多洗一本\n毛衣也为你准备多一层\n但是 你孤单时刻 安慰的体温\n怎么为你多留一份\n我不愿让你一个人 一个人在人海浮沉\n我不愿 你独自走过 风雨的时分\n我不愿让你一个人 承受这世界的残忍\n我不愿眼泪陪你到永恒\n你走后 爱情的遗迹像是空城\n遗落你杯子手套和笑声\n最后你只带走你脆弱和单纯\n和我最放不下的人\n也许未来你会找到懂你疼你更好的人\n下段旅程 你一定要更幸福丰盛\n我不愿让你一个人 一个人在人海浮沉\n我不愿 你独自走过 风雨的时分\n我不愿让你一个人 承受这世界的残忍\n我不愿眼泪陪你到永恒\n你说呢 明知你不在还是会问\n只因习惯你满足的眼神\n只是我最后一个奢求的可能\n只求你有快乐人生\n只求命运带你去一段全新的旅程\n往幸福的天涯飞奔\n别回头 就往前飞奔\n请忘了我 还一个人\n",
    "comments": [
        {
            "content": "其实分别也没有这么可怕。65万个小时后，当我们氧化成风，就能变成同一杯啤酒上两朵相邻的泡沫，就能变成同一盏路灯下两粒依偎的尘埃。宇宙中的原子并不会湮灭，而我们，也终究会在一起",
            "username": "我的文档🏍🏁🚶🏿🚶🏿",
            "time": "2019-09-22 14:34:03"
        },
        {
            "content": "我的宝贝儿子，我不愿让你一个人，去面对这个炎凉的社会，但你终究要习惯孤独。愿你以后能和相爱的人携手看遍世间繁华",
            "username": "淼淼🎀",
            "time": "2019-05-09 09:06:33"
        },
        {
            "content": "2021年。还有人在听吗",
            "username": "肆丶意妄为",
            "time": "2021-04-21 00:53:49"
        },
        {
            "content": "我听这首歌只有一个想法 我们不愿让你一个人啊，阿信",
            "username": "夕屋酱",
            "time": "2019-10-15 00:51:53"
        },
        {
            "content": "董卿写过一段话 无论我们最后生疏成什么样子 曾经对你的好都是真的 就算终有一散 也别辜负相遇 希望你不后悔认识我 也是真的快乐过 如果能回到从前 我会选择不认识你 不是我后悔 是我不能面对现在的结局",
            "username": "花式小清新大叔",
            "time": "2021-11-10 22:42:50"
        }
    ]
}