{
    "name": "风继续吹",
    "id": 319718,
    "artist": "张国荣",
    "artistid": 833,
    "pic": "https://img4.kuwo.cn/star/albumcover/120/s4s5/43/1615847222.jpg",
    "releasedate": "2018-04-01",
    "duration": 310,
    "album": "常在心头",
    "original_url": "https://www.kuwo.cn/play_detail/319718",
    "lyrics": "风继续吹 - 张国荣 (Leslie Cheung)\n词：郑国江\n曲：Ryudo Uzaki,Youko Agi\n我劝你早点归去\n你说你不想归去\n只叫我抱着你\n悠悠海风轻轻吹冷却了野火堆\n我看见伤心的你\n你说我怎舍得去\n哭态也绝美\n如何止哭\n只得轻吻你发边让风继续吹\n不忍远离\n心里极渴望\n希望留下伴着你\n风继续吹\n不忍远离\n心里亦有泪不愿流泪望着你\n过去多少快乐记忆\n何妨与你一起去追\n要将忧郁苦痛洗去\n柔情蜜意我愿记取\n要强忍离情泪\n未许它向下垂\n愁如锁眉头聚\n别离泪始终要下垂\n我已令你快乐\n你也令我痴痴醉\n你已在我心\n不必再问记着谁\n留住眼里每滴泪\n为何仍断续流默默垂\n我劝你早点归去\n你说你不想归去\n只叫我抱着你\n悠悠海风轻轻吹冷却了野火堆\n我看见伤心的你\n你说我怎舍得去\n哭态也绝美\n如何止哭\n只得轻吻你发边让风继续吹\n不忍远离\n心里极渴望\n希望留下伴着你\n风继续吹\n不忍远离\n心里亦有泪不愿流泪望着你\n过去多少快乐记忆\n何妨与你一起去追\n要将忧郁苦痛洗去\n柔情蜜意我愿记取\n要强忍离情泪\n未许它向下垂\n愁如锁眉头聚\n别离泪始终要下垂\n我已令你快乐\n你也令我痴痴醉\n你已在我心\n不必再问记着谁\n留住眼里每滴泪\n为何仍断续流默默垂\n为何仍断续流默默垂\n为何仍断续流默默垂\n",
    "comments": [
        {
            "content": "当年的发哥风流倜傥，当年的哥哥潇洒无双，当年的红姑艳压群芳。三个靓人在最美好的时光在浪漫的巴黎，拍了一部浪漫的电影。三个靓人在红色敞篷车上大笑，这样的亮丽风景只出现了一次。致敬经典：纵横四海",
            "username": "王不留行",
            "time": "2018-05-20 12:26:19"
        },
        {
            "content": "哥哥，风继续吹这首歌浑然天成，我偶尔在一家书店听到，就一直单曲循环，换多少手机这首歌都留着，在最困难的时候是这首歌陪着我，现在好多了，谢谢哥哥！",
            "username": "雨💤笑",
            "time": "2018-03-28 01:30:37"
        },
        {
            "content": "六十二岁的张国荣先生，生辰快乐[心]",
            "username": "很酷的熙",
            "time": "2018-09-12 14:14:56"
        },
        {
            "content": "我是00后但我依然觉得现在的歌星都不能和你比",
            "username": "赤红之瞳",
            "time": "2018-08-03 19:41:03"
        },
        {
            "content": "看了你的视频，这首歌你是哭着唱完的，你走的时候我还小，了解你以后，痛惜",
            "username": "昵称",
            "time": "2018-06-12 00:41:39"
        }
    ]
}