{
    "name": "处处吻",
    "id": 93890,
    "artist": "杨千嬅",
    "artistid": 1367,
    "pic": "https://img4.kuwo.cn/star/albumcover/120/57/52/2562818754.jpg",
    "releasedate": "2014-08-01",
    "duration": 199,
    "album": "电光幻影",
    "original_url": "https://www.kuwo.cn/play_detail/93890",
    "lyrics": "处处吻 - 杨千嬅 (Miriam Yeung)\n词：林夕\n曲：雷颂德\n你爱热吻却永不爱人\n练习为乐但是怕熟人\n你爱路过去索取见闻\n陌路人变得必有份好感\n你热爱别离\n再合再离\n似花瓣献技\n叫花粉遍地 噢噢\n你在播弄这穿线游戏\n跟他结束\n他与她再一起\n你小心\n一吻便颠倒众生\n一吻便救一个人\n给你拯救的体温\n总会再捐给某人\n一吻便偷一个心\n一吻便杀一个人\n一寸吻感一寸金\n一脸崎岖的旅行\n让半夜情人\n延续吻别人\n让你旧情人\n又惠顾他人\n每晚大概有上亿个人\n在地球上落力的亲吻\n你那习惯散播给众人\n在地球上惠泽遍及世人\n你热爱别离\n再合再离\n似花瓣献技\n叫花粉遍地 噢噢\n你在播弄这穿线游戏\n跟他结束\n她与他再一起\n你小心 一吻便颠倒众生\n一吻便救一个人\n给你拯救的体温\n总会再捐给某人\n一吻便偷一个心\n一吻便杀一个人\n一寸吻感一寸金\n一脸崎岖的旅行\n你为何未曾尽兴\n这塑胶的爱情\n跳蚤的旅程\n延展偷天盖地\n好本领\n这吊诡的爱情\n播种的旅程\n别了她 她吻他\n他吻她吻他吻她\n延续愉快过程\n你我他真高兴\n下个她 她吻他\n他吻她再亲你结束这旅程\n多得你这煞星\n你小心\n一吻便颠倒众生\n一吻便救一个人\n给你拯救的体温\n总会再捐给某人\n一吻便偷一个心\n一吻便杀一个人\n一寸吻感一寸金\n一脸崎岖的旅行\n别了她 她吻他\n他吻她吻他吻她\n延续愉快过程\n你我他真高兴\n下个她\n她吻他\n他吻她吻他吻她\n延续愉快过程\n你我他真高兴\n十个她 千个她\n恩爱扩展的旅程\n",
    "comments": [
        {
            "content": "一个月前才找到这首歌，都是免费的现在，火了开始收费，呵呵。",
            "username": "魂影",
            "time": "2020-03-12 11:08:46"
        },
        {
            "content": "抖音到底是把多少歌。给听成收费的了！",
            "username": "娥",
            "time": "2020-03-16 16:12:39"
        },
        {
            "content": "你爱人吻却永不爱人 （内爱羊蛮可wing八爱羊） 练习为乐但是怕熟人 （林砸歪落但系爬缩羊） 你爱路过去索取见闻 （内爱漏锅灰说翠gin门） 陌路人便特别有份好感 （马漏羊bin哒比瑶凡后港） /*******************************/ 你亦爱别离 再合再离 （内亦爱比类 拽哈拽类） 似花瓣献技 叫花粉遍地 喔～喔～ （启发反hin给 giu发凡拼得 喔～喔～） 你在播弄这穿线游戏 （内拽波弄结cyun新要黑） 跟他结束 他与她再一起 （跟他给错 他与她拽呀嘿） /*******************************/ 你小心 一吻便颠倒众生 （内羞森 呀蛮冰",
            "username": "kw1583503624355",
            "time": "2020-03-20 02:44:52"
        },
        {
            "content": "像是哥哥的倾倒众生 像是小李子的深情不悔 像是王祖贤的风华绝代 像是兰普林的风姿绰约 那些美人， 一吻便颠倒众生，一吻便救一个人 一吻便偷一个心，一吻便杀一个人 惊艳时光，温柔岁月",
            "username": "紫月幽魔灵",
            "time": "2020-02-04 13:54:15"
        },
        {
            "content": "有没有B站剪辑来的",
            "username": "nobody",
            "time": "2020-03-27 10:04:12"
        }
    ]
}