{
    "name": "周传雄",
    "id": 2,
    "aartist": "Steve Chou",
    "artistFans": 147165,
    "albumNum": 42,
    "mvNum": 118,
    "musicNum": 754,
    "pic": "https://star.kuwo.cn/star/starheads/120/s4s95/24/2287545672.jpg",
    "birthday": "1969-06-07",
    "birthplace": "台湾",
    "region": "中国台湾",
    "gender": "男",
    "weight": "68kg",
    "height": "178cm",
    "language": "国语;",
    "constellation": "双子座",
    "info": "中文名:周传雄\n 外文名:Steve Chou\n 别名:小刚\n 国籍:中国\n 出生地:台湾台中市\n 职业:歌手\n 经纪公司:熊焱国际演艺经纪（北京）有限公司\n 身高:178cm\n 体重:68kg\n 血型:O型\n 星座:双子座\n 民族:汉族\n 出生日期:1969年6月7日\n 祖籍:湖北公安\n 代表作品:《哈萨雅琪》、《我的心太乱》、《黄昏》、《寂寞沙洲冷》、《青花》、《关不上的窗》\n 生肖:鸡\n 毕业院校:东南工专土木科环保组\n 主要成就:2009音乐大典-年度最佳唱作人  2007第一届无线音乐俱乐部颁奖典礼年度最畅销作曲奖  2006东南劲爆音乐榜最佳制作人、专辑、唱作男歌手等5项大奖\n\n周传雄，曾用艺名小刚。1969年6月7日生于台湾省台中市，台湾歌手、音乐制作人。1989年以艺名“小刚”踏入歌坛，原以偶像歌手包装，1992年以一曲《哈萨雅琪》走红；1998年开始以本名发表作品 ，逐渐展现其创作实力。\n2003年受邀为上海东方广播电台动感101制作并演唱台歌，。2004年受聘内地光线传播娱乐中心音乐总监并为其制作主题曲。 2004年以来已经发布8张个人专辑。2014年11月11日发行专辑《时不知归》。2015年9月，举办“时不知归”全球巡回演唱会2017年9月，化名为“哎呀我打翻了调色板”参加江苏卫视音乐挑战类真人秀节目《蒙面唱将猜猜猜第二季》的录制。\n 从艺历程:周传雄，1987年 开始参加校际音乐创作大赛。  1988年 因校园歌唱比赛而出道，放弃加入小虎队，转为个人发展。\n1989年 以艺名“小刚”推出第一张唱片《无名小卒合辑》。\n1992年 歌曲《哈萨雅琪》奠定了他创作型偶像歌手的地位。\n1997年 发行专辑《我的心太乱》。同年赴英国沉淀，学习语言。\n1998年改回本名周传雄，以大胡子形象重新进入歌坛。  \n2000年12月28日 第9张个人专辑《Transfer》由新力发行。\n2003年12月周传雄与星世代娱乐总裁徐毅共同组建了“哈萨雅琪”（Hasayake）音乐工作室，主要经营艺人经纪和唱片制作。 \n2004年 以歌手的身份在新加坡举办举办“我在身边”大型售票演唱会  ；同年获得新加坡Y.E.S 933醉心金曲奖-年度IFPI全年销量冠军（同年角逐者周杰伦、陶喆、孙燕姿）、加盟环球唱片发行专辑《男人海洋》。\n2005年6月29日 发布专辑《星空下的传说》  。\n2006年6月16日 发布专辑《快乐练习曲》  。\n2007年10月25日 发布专辑《蓝色土耳其》  。\n2009年 发行专辑《恋人创世纪》 ；同年荣获音乐大典年度最佳唱作人。 \n2011年4月23日发行专辑《微凉的记忆》。\n2012年10月12日 发行专辑《打扰爱情》  ，并斩获音乐先锋榜2012年度“年度最佳专辑”、“年度K歌王”、“最佳创作歌手”三项大奖。 \n2014年11月11日 发行专辑《时不知归》 。\n2015年9月，举办“时不知归”全球巡回演唱会。\n2016年8月30日， 推出个人原创歌曲《今宵酒醒何处》 。2017年9月，化名为“哎呀我打翻了调色板”参加江苏卫视音乐挑战类真人秀节目《蒙面唱将猜猜猜第二季》的录制。\n 荣誉记录:2003年 受邀为上海东方广播电台动感101制作并演唱台歌\n2003年 度内地中央人民广播电台-华夏原创金曲榜港台地区最佳男歌手-周传雄《我在身边》《给你的歌》\n2004年 受聘内地光线传播娱乐中心音乐总监并为其制作主题曲\n2004年 周传雄 新加坡举办“我在身边”大型售票演唱会\n2004年 新加坡Y.E.S 933醉心金曲奖-年度IFPI全年销量冠军（同年角逐者周杰伦、陶喆、孙燕姿）\n2004年 加盟环球唱片发行“男人 海洋”专辑\n2005 TOM网络娱乐英雄盛典 - 年度最受网民欢迎港台男歌手奖\n2006年 上海举办“爱，无所不在”大型售票演唱会\n2006年 中国原创歌曲总评榜-港台最佳唱作人奖\n2006年 东南劲爆音乐榜- 最佳制作人、最佳专辑、港台最佳唱作男歌手等5项大奖\n2006年 娱乐中国·2006星光大典- QQ音乐销量奖、风尚男歌手奖\n2006年 TOM网络娱乐英雄盛典 - 最佳音乐专辑奖\n2006年  新城国语力颁奖典礼 - 制作人大奖、新城国语力歌曲奖\n2007 第一届无线音乐俱乐部颁奖典礼 - 年度最畅销作曲奖\n2009 音乐大典-年度最佳唱作人\n2013 音乐先锋榜2012年度颁奖典礼   《打扰爱情》\n\n",
    "song_list": [
        320462,
        1044318,
        492209,
        111658,
        492211,
        51498064,
        4278514,
        92041,
        156404,
        5052923,
        155639329,
        6874743,
        51498063,
        199059600,
        256763505,
        1033996,
        320463,
        156306,
        1044316,
        473672509
    ],
    "original_url": "https://www.kuwo.cn/singer_detail/2"
}