{
    "name": "时光",
    "id": 27811583,
    "artist": "许巍",
    "artistid": 1158,
    "pic": "https://img4.kuwo.cn/star/albumcover/120/24/54/2526977839.jpg",
    "releasedate": "2006-09-01",
    "duration": 305,
    "album": "曾经的你",
    "original_url": "https://www.kuwo.cn/play_detail/27811583",
    "lyrics": "时光 - 许巍\n词：许巍\n曲：许巍\n编曲：许巍\n在阳光温暖的春天\n走在这城市的人群中\n在不知不觉的一瞬间\n又想 起你\n你是记忆中最美的春天\n是我难以再回去的昨天\n你像鲜花那样地绽放\n让我 心动\nWe   say    \nWe   say    \nWe   say    \nWe   say    \n在阳光温暖的春天\n走在这城市的人群中\n在不知不觉的一瞬间\n又想 起你\n也许就在这一瞬间\n你的笑容依然如晚霞般\n在川流不息的时光中\n神采 飞扬\nWe   say    \nWe   say    \nWe   say    \nWe   say    \nWe   say    \nWe   say    \nWe   say    \nWe   say    \nWe   say    \nWe   say    \nWe   say    \nWe   say    \nWe   say    \nWe   say    \nWe   say    \nWe   say\n",
    "comments": [
        {
            "content": "2021年还有人在听这首歌的请给个赞！",
            "username": "洪",
            "time": "2021-04-20 20:59:26"
        },
        {
            "content": "听这首歌，会想起很多美好的东西，舒服！",
            "username": "爱听音乐的先生",
            "time": "2018-01-12 00:05:08"
        },
        {
            "content": "那些翻着评论，却不评论的人，或许才是真正的孤独寂寞的人，路过的陌生人，愿你贪吃不胖，愿你懒惰不丑，愿你的深情不被辜负，愿你的余生都有人陪假如你活到八十岁，一共29200天70万个小时，4200万分钟，差不多25亿秒左右，这10秒你在读我的评论，这十秒你只属于我，你好，陌生人。",
            "username": "烙印",
            "time": "2022-06-19 06:13:29"
        },
        {
            "content": "我最喜欢这首歌",
            "username": "尘土飞扬",
            "time": "2019-05-04 20:00:46"
        },
        {
            "content": "想想来深圳已有20载，可是留下的只有回忆，没有干出什么成绩，从20岁的小伙，到现在成为名副其实的大叔，人生有太多遗憾……，每当听到这首歌时，都让我回忆很久",
            "username": "*****",
            "time": "2020-03-14 01:37:49"
        }
    ]
}