{
    "name": "改变自己",
    "id": 271337,
    "artist": "王力宏",
    "artistid": 1416,
    "pic": "https://img4.kuwo.cn/star/albumcover/120/s3s4/25/619744070.jpg",
    "releasedate": "2007-07-13",
    "duration": 194,
    "album": "改变自己",
    "original_url": "https://www.kuwo.cn/play_detail/271337",
    "lyrics": "改变自己 - 王力宏 (Leehom Wang)\n词：王力宏\n曲：王力宏\n今早起床了\n看镜子里的我\n忽然发现我发型\n睡得有点Kuso\n一点点改变\n有很大的差别\n你我的力量\n也能改变世界\n最近比较烦\n最近情绪很Down\n每天看新闻\n都会很想大声尖叫\n但脏话没用\n大家只会嫌凶\n我改变自己\n发现大有不同\n新一代的朋友\n我们好好的加油\n大家一起大声地说\nNa na na na na\n我可以改变世界\n改变自己\n改变隔膜\n改变小气\n要一直 努力 努力\n永不放弃\n才可以改变世界\nCome on 改变自己\n今早起床了\n觉得头有点痛\n可能是二氧化碳太多\n氧气不够\n一点点改变\n有很大的差别\n你我的热情\n也能改变世界\n只能代表自己\n没有政治立场\n即使这世界\n让我看得十分紧张\n要调整自己\n没想到一点\n就能画龙点睛\n新一代的朋友\n我们好好的加油\n大家一起大声地说\nNa na na na na\n我可以改变世界\n改变自己\n改变隔膜\n改变小气\n要一直 努力 努力\n永不放弃\n才可以改变世界\nCome on 改变自己\n我可以改变世界\n改变自己\n改变隔膜\n改变小气\n要一直 努力 努力\n永不放弃\n才可以改变世界\nCome on 改变自己\n",
    "comments": [
        {
            "content": "看了跑男过后才来听的😂",
            "username": "情绪控Design",
            "time": "2017-06-16 22:51:29"
        },
        {
            "content": "这首歌比TFBOYS的歌好多了",
            "username": "qq1484104656",
            "time": "2017-01-07 13:55:27"
        },
        {
            "content": "鹿哥最近唱王力宏的歌比自己的都多！",
            "username": "最爱的红绳",
            "time": "2017-06-17 04:45:41"
        },
        {
            "content": "但歌曲好听呀！！！你不觉得好听吗？？？俩元不坑人，你呀，不知走了什么狗屎运了，还嫌弃呢，你怎么这么不知好歹啊！！！！！觉得我说的对的，请帮我顶一下，谢谢大家了。。。。。。。",
            "username": "kuwo1484792770",
            "time": "2017-01-22 22:32:39"
        },
        {
            "content": "别提鹿晗了好吗？跟王力宏不是一个档次的",
            "username": "小八",
            "time": "2017-12-01 11:21:31"
        }
    ]
}