{
    "name": "清明客",
    "id": 215391882,
    "artist": "李玉刚",
    "artistid": 3913,
    "pic": "https://img4.kuwo.cn/star/albumcover/120/s4s31/95/624195772.jpg",
    "releasedate": "2022-04-04",
    "duration": 296,
    "album": "追风赶月的你",
    "original_url": "https://www.kuwo.cn/play_detail/215391882",
    "lyrics": "清明客 - 李玉刚\n词：白金明\n曲：宋涛/霄磊\n制作人：王壮\n混音：姚坤\n出品人：王春风/陆瑒\n发行人：周文惠\n音乐项目总监：宫尹琳Rainie\n项目合作统筹：蔡安丽\n总企划：温瑞梁/Frank/李明/马琳璇\n视觉设计：李垌\n音乐出品：玉泽东方（北京）文化传媒有限公司\n清明客 恋雨声\n一枝故柳\n比天地还重\n情深者 懂南风\n吹开故梦\n是你在心中\n不系之舟 游万古而并影青松\n桨动长河 出昆仑而浩荡弯弓\n清明客 不避雨也不等落虹\n过人间 俗笔下我无名无踪\n于晨 于暮 于小巷筛酒\n一碗浮生一碗空\n于悲 于欢 于大墨执手\n半袖逍遥半袖风\n清明客 恋雨声\n一枝故柳\n比天地还重\n情深者 懂南风\n吹开故梦\n是你在心中\n杏花重情 心海风干一夜浅红\n沉烟一缕 这也是我思念无功\n墨太旧 青白相染阴阳难通\n泪顿时 山水是你不灭不生\n于晨 于暮 于小村听梦\n一声笑语一声钟\n于悲 于欢 于大月对影\n半生给你半生空\n清明客 恋雨声\n一枝故柳\n比天地还重\n情深者 懂南风\n吹开故梦\n是你在心中\n吹开故梦\n是你在心中\n",
    "comments": [
        {
            "content": "我今年16岁了，可以给我16个赞吗？",
            "username": "不晓得怎么取名字",
            "time": "2022-04-05 08:55:35"
        },
        {
            "content": "好听是李玉刚的粉丝，右上角点一下😉😉",
            "username": "xcd",
            "time": "2022-04-04 21:08:27"
        },
        {
            "content": "让我看看李玉刚这几个字值多少个赞→",
            "username": "灼骨炎阳",
            "time": "2022-04-05 22:01:13"
        },
        {
            "content": "“月亮很亮，亮也没用，没用也亮;我喜欢你，喜欢没用，没用也喜欢.”",
            "username": "我叫谢文浩",
            "time": "2022-04-05 13:34:14"
        },
        {
            "content": "爱国者，都应该受尊重",
            "username": "爱吃草的鱼",
            "time": "2022-04-09 21:17:38"
        }
    ]
}