{
    "name": "越过山丘",
    "id": 26445014,
    "artist": "杨宗纬",
    "artistid": 5265,
    "pic": "https://img4.kuwo.cn/star/albumcover/120/s4s23/11/2028233130.jpg",
    "releasedate": "2017-07-21",
    "duration": 233,
    "album": "越过山丘",
    "original_url": "https://www.kuwo.cn/play_detail/26445014",
    "lyrics": "越过山丘 - 杨宗纬 (Aska Yang)\n词：高晓松\n曲：高晓松\n越过山丘\n遇见十九岁的我\n戴着一双白手套\n喝着我的喜酒\n他问我幸福与否\n是否永别了忧愁\n为何婚礼上那么多人\n没有一个当年的朋友\n我说我曾经挽留\n他们纷纷去人海漂流\n那个你深爱的小妞\n嫁了隔壁的王某\n我问她幸福与否\n她哭着点了点头\n后来遇见过那么多人\n想对你说却张不开口\n就让我随你去\n让我随你去\n回到二十岁狂奔的路口\n做个形单影只的歌手\n就让我随你去\n让我随你去\n逆着背影婆娑的人流\n向着那座荒芜的山丘\n挥挥衣袖\n越过山丘\n遇见六十岁的我\n拄着一根白手杖\n在听鸟儿歌唱\n我问他幸福与否\n他笑着摆了摆手\n在他身边围绕着一群\n当年流放归来的朋友\n他说你不必挽留\n爱是一个人的等候\n等到房顶开出了花\n这里就是天下\n总有人幸福白头\n总有人哭着分手\n无论相遇还是不相遇\n都是献给岁月的序曲\n就让我随你去\n让我随你去\n去到六十岁停下的渡口\n等着被一条小船接走\n就让我随你去\n让我随你去\n随着熙熙攘攘的人流\n向着开满鲜花的山丘\n挥挥衣袖\n越过山丘\n遇见十九岁的我\n戴着一双白手套\n喝着我的喜酒\n他问我幸福与否\n是否永别了忧愁\n为何婚礼上那么多人\n没有一个当年的朋友\n",
    "comments": [
        {
            "content": "每个人在听歌时候都会有不一样的体会，轻而易举便能直击人心。\n以前听歌，听的是旋律\n然后听歌，听的是歌词\n后来听歌，听的是故事\n现在听歌，听的是自己",
            "username": "破天",
            "time": "2017-07-20 17:00:50"
        },
        {
            "content": "晓松在48岁的词写的越来越走心了",
            "username": "懒得取名字",
            "time": "2017-07-22 23:13:38"
        },
        {
            "content": "无限循环了这么久，才终于明白了歌词的意思。回忆青春，苦涩满溢，多想再次重来，却终究还是会老去，而身边围绕着的却是重又归来的旧友，用爱等候，一生之久。你是想等候，还是越过？",
            "username": "私奔的雨天",
            "time": "2017-08-11 10:45:38"
        },
        {
            "content": "2017年最经典的歌曲",
            "username": "长门",
            "time": "2017-07-22 16:09:01"
        },
        {
            "content": "这是高晓松致敬李宗盛的一首歌 很有味道。[棒]",
            "username": "鲁班大师智商250",
            "time": "2017-07-21 23:47:29"
        }
    ]
}