{
    "name": "爱拼才会赢",
    "id": 1027626,
    "artist": "卓依婷&林正桦",
    "artistid": 1890,
    "pic": "https://img4.kuwo.cn/star/albumcover/120/s4s96/58/816783149.jpg",
    "releasedate": "1995-03-01",
    "duration": 214,
    "album": "闽南语情歌大对唱",
    "original_url": "https://www.kuwo.cn/play_detail/1027626",
    "lyrics": "爱拼才会赢 - 卓依婷 (Timi Zhuo)/林正桦\n词：陈百潭\n曲：陈百潭\n编曲：陈百潭\n女：\n一时失志不免怨叹\n男：\n一时落魄不免胆寒\n那通失去希望\n每日醉茫茫\n女：\n无魂有体亲像稻草人\n人生可比是海上的波浪\n男：\n有时起有时落\n女：\n好运\n男：\n歹运\n女：\n总嘛照起工来行\n三分天注定\n男：\n七分靠打拼\n合：\n爱拼才会赢\n女：\n一时失志不免怨叹\n男：\n一时落魄不免胆寒\n那通失去希望\n每日醉茫茫\n女：\n无魂有体亲像稻草人\n人生可比是海上的波浪\n男：\n有时起有时落\n女：\n好运\n男：\n歹运\n女：\n总嘛照起工来行\n三分天注定\n男：\n七分靠打拼\n合：\n爱拼才会赢\n女：\n人生可比是海上的波浪\n男：\n有时起有时落\n女：\n好运\n男：\n歹运\n女：\n总嘛照起工来行\n三分天注定\n男：\n七分靠打拼\n合：\n爱拼才会赢\n",
    "comments": [
        {
            "content": "好听好听好听",
            "username": "有姝",
            "time": "2016-12-21 21:49:23"
        },
        {
            "content": "依婷为什么你的歌还收费",
            "username": "韩彬",
            "time": "2017-09-02 13:03:00"
        },
        {
            "content": "以大期小被狗咬。你就是。[鄙视][鄙视][吐][吐][不屑][不屑][大笑][差][差]",
            "username": "美丽天使",
            "time": "2016-10-05 13:48:50"
        },
        {
            "content": "大爱❤淘宝，租个会员，用起来太好了🙅",
            "username": "麦茶娘",
            "time": "2017-02-22 23:06:21"
        },
        {
            "content": "这首经典歌曲，竟然还要收费。准备收入囊中，尴尬了。",
            "username": "气质范女王",
            "time": "2017-06-10 13:55:26"
        }
    ]
}