{
    "name": "终于失去你（我终于终于终于失去你）",
    "id": 451899960,
    "artist": "任夏",
    "artistid": 3840290,
    "pic": "https://img4.kuwo.cn/star/albumcover/120/s4s32/13/1826024492.jpg",
    "releasedate": "2025-01-16",
    "duration": 208,
    "album": "终于失去你",
    "original_url": "https://www.kuwo.cn/play_detail/451899960",
    "lyrics": "终于失去你（我终于终于终于失去你）\n作词：任夏\n作曲：任夏/曲多美\n演唱：任夏\n编曲：建行\n吉他：赵翔\n和声编写/和声：谌宥\n人声编辑：迟色\n混音：汤宝\n制作人：何文宇\n制作统筹：谌宥/翊学长\n宣发策划：陶文/韦仕论/黄亚轩/郭禹婷\n宣发总监：王倩/黄超亚\n监制：王腾飞\n宣发：星云计划x 一米星空\n艺人经纪：韦耀\n发行人：韦琪\n发行公司：万象星云\n『听歌就在中国酷狗*星曜计划』\n你眼睛为何不敢看着我\n是不是还没想好怎么说\n哪天起你对我变得话不多\n我猜到你有离开的选择\n走或留一直都由你抉择\n我何必还要寻求个结果\n感情里若要你一定做个取舍\n你第一个想放弃的就是我\n我终于终于终于失去你\n好可惜只能陪你到这里\n你曾许给我的美梦如今又和谁提起\n你的幸福已经和我没关系\n我终于终于终于失去你\n这结局我实在无能为力\n你就像那自由的风我始终留不住你\n我只能成全你放过我自己\n走或留一直都由你抉择\n我何必还要寻求个结果\n感情里若要你一定做个取舍\n你第一个想放弃的就是我\n我终于终于终于失去你\n好可惜只能陪你到这里\n你曾许给我的美梦如今又和谁提起\n你的幸福已经和我没关系\n我终于终于终于失去你\n这结局我实在无能为力\n你就像那自由的风我始终留不住你\n我只能成全你放过我自己\n",
    "comments": [
        {
            "content": "哪吒来的",
            "username": "回忆如墓",
            "time": "2025-02-21 14:30:10"
        }
    ]
}