{
    "name": "岁岁",
    "id": 314109306,
    "artist": "任素汐",
    "artistid": 493402,
    "pic": "https://img4.kuwo.cn/star/albumcover/120/s3s7/30/3594947230.jpg",
    "releasedate": "2023-11-05",
    "duration": 216,
    "album": "故乡，别来无恙 电视剧原声带",
    "original_url": "https://www.kuwo.cn/play_detail/314109306",
    "lyrics": "岁岁 (《故乡，别来无恙》电视剧重逢曲) - 任素汐\n词：任素汐\n曲：任素汐\n编曲：谢葳蕤@勇士音乐\n制作人：安鑫@勇士音乐\n音乐监制：钱雷@勇士音乐\n配唱：安鑫@勇士音乐\n贝斯：安鑫@勇士音乐\n吉他：胡洋\n口琴：刘晓光\n混音：姚海毅@勇士音乐\n音乐制作：勇士音乐/奔跑怪物\n发行：百纳娱乐/云海娱乐\n推广：麻雀音乐人\n那天夕阳透过枝桠扫射我\n影子重叠你追我赶笑声癫\n那天脸斑驳\n那天最后一面\n那天天好高\n高过不相见\n去过去溜达了半晌\n没见你模样\n那时我 半米高\n翻不了院墙\n说来怪 谁递了我天梯\n翻过去 我翻过去了\n好久不见\n去过去溜达了半晌\n没见你模样\n那时我 半米高\n翻不了院墙\n说来怪 谁递了我天梯\n翻过去 我翻过去了\n好久不见\n谁递了我天梯\n翻过去 我翻过去了\n好久不见\n那天夕阳透过枝桠扫射我\n影子重叠你追我赶笑声癫\n那天脸斑驳\n那天最后一面\n那天天好高\n高过不相见\n",
    "comments": [
        {
            "content": "人生啊，哪有什么两全之策，短短百年，不过是教人取舍罢了，手持烟火以谋生，且停，且忘，且随风；且行，且看，且从容！ 人字有两笔，一撇写前半生，一捺写后半生，前半生写执着，后半生写释怀！ 生活，一半烟火，一半清欢，人生，一半清醒，一半释然，不念过往，不畏将来，愿今后的日子，阳光清澈，世事皆温柔！",
            "username": "执手看流年",
            "time": "2023-11-15 20:42:22"
        },
        {
            "content": "故乡是我们年少时想要逃离的地方，是我们年老想回，可能已经回不去的地方。",
            "username": "阿呆",
            "time": "2023-11-11 15:57:36"
        },
        {
            "content": "我们要经历什么，才会变成大人？要为平凡所困，要为世故抱歉。要习惯披星戴月的重复，要知晓脆弱但能抵御来日幻变。书本里讳莫如深的总结，远不如当下这漫长的课堂，而那些忍住的眼泪，在遥远的以后，变成时间的珍珠，被浪花涤净，冲回少年的脚边。",
            "username": "北极星的眼泪",
            "time": "2023-11-25 23:44:31"
        },
        {
            "content": "词曲演唱都是任素汐，好有才[棒]",
            "username": "脑阔疼",
            "time": "2023-11-24 13:05:00"
        },
        {
            "content": "有没有和我一样每次听都眼泪止不住的 大老爷们一枚 太奇怪了",
            "username": "光子光",
            "time": "2023-11-20 20:52:44"
        }
    ]
}