{
    "name": "亲密爱人",
    "id": 166900,
    "artist": "梅艳芳",
    "artistid": 1127,
    "pic": "https://img4.kuwo.cn/star/albumcover/120/76/69/706411757.jpg",
    "releasedate": "2018-04-01",
    "duration": 299,
    "album": "追忆似水芳华",
    "original_url": "https://www.kuwo.cn/play_detail/166900",
    "lyrics": "亲密爱人 - 梅艳芳\n词：小虫\n曲：小虫\n今夜还吹着风 想起你好温柔\n有你的日子份外的轻松\n也不是无影踪 只是想你太浓\n怎么会无时无刻把你梦\n爱的路上有你 我并不寂寞\n你对我那么的好 这次真的不同\n也许我应该好好把你拥有\n就像你一直为我守候\n亲爱的人 亲密的爱人\n谢谢你这么长的时间陪着我\n亲爱的人 亲密的爱人\n这是我一生中最兴奋的时分\n今夜还吹着风 想起你好温柔\n有你的日子份外的轻松\n也不是无影踪 只是想你太浓\n怎么会无时无刻把你梦\n爱的路上有你 我并不寂寞\n你对我那么的好 这次真的不同\n也许我应该好好把你拥有\n就像你一直为我守候\n亲爱的人 亲密的爱人\n谢谢你这么长的时间陪着我\n亲爱的人 亲密的爱人\n这是我一生中最兴奋的时分\n",
    "comments": [
        {
            "content": "经典好歌，百听不厌，经常单曲循环一晚上。",
            "username": "不惑",
            "time": "2017-11-04 21:38:40"
        },
        {
            "content": "我最怕看到的，不是两个相爱的人互相伤害，而是两个爱了很久很久的人突然分开了，像陌生人一样擦肩而过。我受不了那种残忍的过程，因为我不能明白当初植入骨血的亲密，怎么会变为日后两两相忘的冷漠。",
            "username": "野王哥哥滴滴我",
            "time": "2018-02-12 16:40:08"
        },
        {
            "content": "什么是经典呢，就是不管你在喜怒哀乐的时候，当听到他都能勾起你最平静最快乐的情绪，大爱！",
            "username": "超的虹",
            "time": "2018-01-01 14:48:13"
        },
        {
            "content": "随着年龄的增长 越来越明白老歌的魅力",
            "username": "笑开颜✿",
            "time": "2018-11-14 21:44:34"
        },
        {
            "content": "婵女观光团[可爱]",
            "username": "*****",
            "time": "2018-01-01 20:02:55"
        }
    ]
}