{
    "name": "微微",
    "id": 540826,
    "artist": "郭顶",
    "artistid": 1610,
    "pic": "https://img4.kuwo.cn/star/albumcover/120/s4s5/94/903485887.jpg",
    "releasedate": "2009-08-18",
    "duration": 211,
    "album": "微微",
    "original_url": "https://www.kuwo.cn/play_detail/540826",
    "lyrics": "微微 - 郭顶\n词：张莹\n曲：郭顶\n（未经著作权人许可不得翻唱翻录或使用）\n浩瀚的海\n无边期待\n人们想问的答案\n它是否存在\n微小的海\n窝在心怀\n用一首歌的光阴温柔澎湃\n微微 去喜欢 这微微\n小世界\n街上边 所有一切\n微微 的倾斜 换视角\n看世界\n变不一样的世界\n微微 小树叶 微微凉\n的季节\n街上边 所有一切\n微微 的倾斜 换视角\n看世界\n变不一样的世界\n发丝渐白\n时间太快\n细小美好的瞬间我\n不愿忽略\n有些人要\n微微去爱\n用一首歌的光阴温柔崇拜\n微微 去喜欢 这微微\n小世界\n街上边 所有一切\n微微 的倾斜 换视角\n看世界\n变不一样的世界\n微微 小树叶 微微凉\n的季节\n街上边 所有一切\n微微 的倾斜 换视角\n看世界\n变不一样的世界\n世界对它的爱人\n把它面具摘下\n藏起了浩瀚\n在耳边唱一支情歌\n如一个吻\n歌声像轻轻的吻\n那夜把思念印上永恒\n浩瀚的海\n无边期待\n而你想问的答案\n它是否存在\n微小的海\n窝在心怀\n用一首歌的光阴温柔澎湃\n",
    "comments": [
        {
            "content": "好像风格就很像，我很努力的听了[大哭]鼓点有点像。但郭顶的新歌风格已经很多变了",
            "username": "*****",
            "time": "2017-06-24 14:00:58"
        },
        {
            "content": "听了飞行器的执行周期过来的，感觉郭老师唱法有一些变化。听这首的建议也去听听新专，非常有想法的一张专辑。",
            "username": "Oceana",
            "time": "2017-05-11 13:46:45"
        },
        {
            "content": "他太低调，总是默默的，不像现在各种随便什么出个作品都自封歌手的牛鬼蛇神……",
            "username": "屌丝",
            "time": "2017-02-04 14:14:34"
        },
        {
            "content": "郭顶的声音带着灵气，而且辨识度很高，学累了，听听他的歌，莫名的还有股感动～～不懂为什么关注他的人这么少[哀伤][哀伤]",
            "username": "风散蛮荒",
            "time": "2017-04-03 19:58:42"
        },
        {
            "content": "真的是青春啊，虽然真的好多年不听了，但是前奏一起来，还能记得怎么哼唱，一直在记忆里吧……希望他能一直做自己喜欢的音乐",
            "username": "回忆，亦是结局",
            "time": "2016-10-30 23:45:27"
        }
    ]
}