{
    "name": "失踪",
    "id": 51419756,
    "artist": "林忆莲",
    "artistid": 1014,
    "pic": "https://img4.kuwo.cn/star/albumcover/120/s4s40/18/2153408201.jpg",
    "releasedate": "2000-01-18",
    "duration": 200,
    "album": "林忆莲's",
    "original_url": "https://www.kuwo.cn/play_detail/51419756",
    "lyrics": "失踪 - 林忆莲 (Sandy Lam)\n词：何启弘\n曲：小柯\n编曲：刘志远\n她说她找不到能爱的人\n所以宁愿居无定所的过一生\n从这个安静的镇\n到下一个热闹的城\n来去自由从来不等红绿灯\n酒吧里头喧哗的音乐声\n让她暂时忘了女人的身份\n放肆摇动着灵魂\n贴着每个耳朵问\n到底哪里才有够好的男人\n没有爱情发生\n她只好趁着酒意释放青春\n刻意凝视每个眼神\n却只看见自己也不够诚恳\n推开关了的门\n在风中晾干脸上的泪痕\n然后在早春陌生的街头狂奔\n直到这世界忘了她这个人\n酒吧里头喧哗的音乐声\n让她暂时忘了女人的身份\n放肆摇动着灵魂\n贴着每个耳朵问\n到底哪里才有够好的男人\n没有爱情发生\n她只好趁着酒意释放青春\n刻意凝视每个眼神\n却只看见自己也不够诚恳\n推开关了的门\n在风中晾干脸上的泪痕\n然后在早春陌生的街头狂奔\n直到这世界忘了她这个人\n推开关了的门\n在风中晾干脸上的泪痕\n然后在早春陌生的街头狂奔\n直到这世界忘了她这个人\n",
    "comments": [
        {
            "content": "这才是歌曲",
            "username": "当我遇上你",
            "time": "2023-08-17 17:01:22"
        },
        {
            "content": "大学里林忆莲的歌循环播放，一晃二十几年。",
            "username": "陆绊",
            "time": "2022-09-02 23:55:43"
        },
        {
            "content": "体会到爱一个人爱到骨子里面，体会到泪流满面的感觉",
            "username": "红尘团_仙儿",
            "time": "2019-06-23 23:10:55"
        },
        {
            "content": "这老娘们的声音  李宗盛果然很懂",
            "username": "秃腾老叔昏吖😳",
            "time": "2024-02-13 18:12:30"
        },
        {
            "content": "红绿灯还是要等一等的",
            "username": "五百万丶",
            "time": "2022-04-10 01:30:18"
        }
    ]
}